tartiflette_plugin_isodatenow/__init__.py
tartiflette_plugin_isodatenow-0.2.2.dist-info/LICENSE
tartiflette_plugin_isodatenow-0.2.2.dist-info/WHEEL
tartiflette_plugin_isodatenow-0.2.2.dist-info/METADATA
tartiflette_plugin_isodatenow-0.2.2.dist-info/RECORD
