Metadata-Version: 2.1
Name: tartiflette-plugin-isodatenow
Version: 0.2.2
Summary: ISO Date Formatter for Tartiflette
Home-page: https://github.com/briggleman/tartiflette-plugin-isodate
License: MIT
Keywords: api,graphql,tartiflette,iso8601,directive
Author: Ben Riggleman
Author-email: ben.riggleman@gmail.com
Requires-Python: >=3.6,<4.0
Classifier: Intended Audience :: Developers
Classifier: License :: OSI Approved :: MIT License
Classifier: Programming Language :: Python :: 3
Classifier: Programming Language :: Python :: 3.6
Classifier: Programming Language :: Python :: 3.7
Classifier: Programming Language :: Python :: Implementation :: PyPy
Classifier: Topic :: Software Development :: Libraries
Requires-Dist: tartiflette (>=0.12.5,<0.13.0)
Project-URL: Repository, https://github.com/briggleman/tartiflette-plugin-isodate
